README.rst
setup.py
svdlib/__init__.py
svdlib/core.py
svdlib.egg-info/PKG-INFO
svdlib.egg-info/SOURCES.txt
svdlib.egg-info/dependency_links.txt
svdlib.egg-info/top_level.txt